heavy/.DS_Store
heavy/__init__.py
heavy-0.1.dist-info/WHEEL
heavy-0.1.dist-info/METADATA
heavy-0.1.dist-info/RECORD
