Metadata-Version: 2.1
Name: heavy
Version: 0.1
Summary: Heavy
Author: HeavyAI
Requires-Python: >=3.8,<4.0
Classifier: Programming Language :: Python :: 3
Classifier: Programming Language :: Python :: 3.10
Classifier: Programming Language :: Python :: 3.8
Classifier: Programming Language :: Python :: 3.9
